extra_boolean/__init__.py
extra_boolean/and_.py
extra_boolean/count.py
extra_boolean/eq.py
extra_boolean/eqv.py
extra_boolean/imp.py
extra_boolean/imply.py
extra_boolean/nand.py
extra_boolean/neq.py
extra_boolean/nimply.py
extra_boolean/nor.py
extra_boolean/not_.py
extra_boolean/or_.py
extra_boolean/parse.py
extra_boolean/select.py
extra_boolean/xnor.py
extra_boolean/xor.py
extra_boolean-1.0.6.dist-info/LICENSE
extra_boolean-1.0.6.dist-info/METADATA
extra_boolean-1.0.6.dist-info/WHEEL
extra_boolean-1.0.6.dist-info/top_level.txt
extra_boolean-1.0.6.dist-info/RECORD
