Metadata-Version: 2.1
Name: extra-boolean
Version: 1.0.6
Summary: Boolean data type has two possible truth values to represent logic.
Home-page: https://python3f.github.io/extra-boolean/
Author: Subhajit Sahu
Author-email: wolfram77@gmail.com
License: MIT License
Project-URL: Source, https://github.com/python3f/extra-boolean/
Project-URL: Documentation, https://python3f.github.io/extra-boolean/
Keywords: extra,boolean,algebra,logic,parse,not,eq,neq,imply,nimply,and,or,xor,count,nand,nor,xnor,select
Platform: UNKNOWN
Classifier: Intended Audience :: Education
Classifier: License :: OSI Approved :: MIT License
Classifier: Operating System :: MacOS :: MacOS X
Classifier: Operating System :: Microsoft :: Windows
Classifier: Operating System :: POSIX
Classifier: Operating System :: POSIX :: BSD
Classifier: Operating System :: POSIX :: Linux
Classifier: Programming Language :: Python :: 2
Classifier: Programming Language :: Python :: 3
Requires-Python: >=2.5
